ccurl.cpython-36m-darwin.so
PyOTA_CCurl-1.0.1.dist-info/DESCRIPTION.rst
PyOTA_CCurl-1.0.1.dist-info/METADATA
PyOTA_CCurl-1.0.1.dist-info/RECORD
PyOTA_CCurl-1.0.1.dist-info/WHEEL
PyOTA_CCurl-1.0.1.dist-info/metadata.json
PyOTA_CCurl-1.0.1.dist-info/top_level.txt
