Metadata-Version: 2.0
Name: PyOTA-CCurl
Version: 1.0.1
Summary: C Curl extension for PyOTA
Home-page: https://github.com/todofixthis/pyota-ccurl
Author: Phoenix Zerin
Author-email: phx@phx.ph
License: MIT
Keywords: iota,tangle,iot,internet of things,api,library,cryptocurrency,balanced ternary
Platform: UNKNOWN
Classifier: Development Status :: 5 - Production/Stable
Classifier: Intended Audience :: Developers
Classifier: License :: OSI Approved :: MIT License
Classifier: Programming Language :: Python :: 3
Classifier: Programming Language :: Python :: 3.5
Classifier: Programming Language :: Python :: 3.6
Classifier: Topic :: Software Development :: Libraries :: Python Modules
Requires-Dist: pyota
